yta_general_utils/__init__.py
yta_general_utils/dimensions/__init__.py
yta_general_utils/experimental/__init__.py
yta_general_utils/experimental/autogui_utils.py
yta_general_utils/experimental/faker/__init__.py
yta_general_utils/experimental/faker/instagram.py
yta_general_utils/experimental/faker/whatsapp.py
yta_general_utils/experimental/image_detection.py
yta_general_utils/experimental/image_processor.py
yta_general_utils/experimental/tiktok.py
yta_general_utils/experimental/video_processor.py
yta_general_utils/logger/__init__.py
yta_general_utils/url/__init__.py
yta_general_utils/url/dataclasses.py
yta_general_utils/url/handler.py
yta_general_utils/url/validator.py
yta_general_utils-0.2.0.dist-info/licenses/LICENSE
yta_general_utils-0.2.0.dist-info/METADATA
yta_general_utils-0.2.0.dist-info/WHEEL
yta_general_utils-0.2.0.dist-info/RECORD
