Metadata-Version: 2.4
Name: yta-general-utils
Version: 0.2.0
Summary: Youtube Autónomo general utils are here.
License-File: LICENSE
Author: danialcala94
Author-email: danielalcalavalera@gmail.com
Requires-Python: ==3.9
Classifier: Programming Language :: Python :: 3
Classifier: Programming Language :: Python :: 3.9
Requires-Dist: numpy (>=1.22.0,<3.0.0)
Requires-Dist: requests (>=2.32.3,<9.0.0)
Requires-Dist: yta_constants (>=0.0.1,<1.0.0)
Requires-Dist: yta_random (>=0.0.1,<1.0.0)
Requires-Dist: yta_validation (>=0.0.1,<1.0.0)
